{
  "timestamp": "2026-05-05T13:56:04.900Z",
  "env": "staging",
  "baseUrl": "https://xo-landing-staging.fly.dev",
  "movesPerUser": 3,
  "rampMs": 80,
  "sweep": [
    1,
    5,
    10,
    25
  ],
  "levels": [
    {
      "concurrency": 1,
      "movesObserved": 3,
      "usersStarted": 1,
      "fatalUsers": 0,
      "partialUsers": 0,
      "summary": {
        "movePostAck": {
          "p50": 166,
          "p95": 197,
          "p99": 197,
          "n": 3
        },
        "playerEvent": {
          "p50": 257,
          "p95": 367,
          "p99": 367,
          "n": 3
        },
        "botMoveTotal": {
          "p50": 257,
          "p95": 367,
          "p99": 367,
          "n": 3
        },
        "lookup": {
          "p50": 3,
          "p95": 4,
          "p99": 4,
          "n": 3
        },
        "apply": {
          "p50": 7,
          "p95": 8,
          "p99": 8,
          "n": 3
        },
        "publishToPickup": {
          "p50": 55,
          "p95": 196,
          "p99": 196,
          "n": 3
        },
        "pickupToWrite": {
          "p50": 0,
          "p95": 1,
          "p99": 1,
          "n": 3
        }
      },
      "moves": [
        {
          "m": 0,
          "concurrency": 1,
          "sseConnectMs": 160,
          "movePostAckMs": 197,
          "playerEventMs": 367,
          "botMoveTotalMs": 367,
          "lookupMs": 4,
          "applyMs": 8,
          "publishToPickupMs": 196,
          "pickupToWriteMs": 1
        },
        {
          "m": 1,
          "concurrency": 1,
          "sseConnectMs": null,
          "movePostAckMs": 160,
          "playerEventMs": 257,
          "botMoveTotalMs": 257,
          "lookupMs": 3,
          "applyMs": 6,
          "publishToPickupMs": 55,
          "pickupToWriteMs": 0
        },
        {
          "m": 2,
          "concurrency": 1,
          "sseConnectMs": null,
          "movePostAckMs": 166,
          "playerEventMs": 218,
          "botMoveTotalMs": 219,
          "lookupMs": 3,
          "applyMs": 7,
          "publishToPickupMs": 48,
          "pickupToWriteMs": 0
        }
      ]
    },
    {
      "concurrency": 5,
      "movesObserved": 15,
      "usersStarted": 5,
      "fatalUsers": 0,
      "partialUsers": 0,
      "summary": {
        "movePostAck": {
          "p50": 189,
          "p95": 260,
          "p99": 260,
          "n": 15
        },
        "playerEvent": {
          "p50": 324,
          "p95": 932,
          "p99": 932,
          "n": 15
        },
        "botMoveTotal": {
          "p50": 324,
          "p95": 932,
          "p99": 932,
          "n": 15
        },
        "lookup": {
          "p50": 3,
          "p95": 7,
          "p99": 7,
          "n": 15
        },
        "apply": {
          "p50": 7,
          "p95": 8,
          "p99": 8,
          "n": 15
        },
        "publishToPickup": {
          "p50": 55,
          "p95": 740,
          "p99": 740,
          "n": 15
        },
        "pickupToWrite": {
          "p50": 0,
          "p95": 0,
          "p99": 0,
          "n": 15
        }
      },
      "moves": [
        {
          "m": 0,
          "concurrency": 5,
          "sseConnectMs": 81,
          "movePostAckMs": 175,
          "playerEventMs": 932,
          "botMoveTotalMs": 932,
          "lookupMs": 2,
          "applyMs": 7,
          "publishToPickupMs": 740,
          "pickupToWriteMs": 0
        },
        {
          "m": 1,
          "concurrency": 5,
          "sseConnectMs": null,
          "movePostAckMs": 171,
          "playerEventMs": 199,
          "botMoveTotalMs": 202,
          "lookupMs": 2,
          "applyMs": 6,
          "publishToPickupMs": 11,
          "pickupToWriteMs": 0
        },
        {
          "m": 2,
          "concurrency": 5,
          "sseConnectMs": null,
          "movePostAckMs": 250,
          "playerEventMs": 313,
          "botMoveTotalMs": 313,
          "lookupMs": 2,
          "applyMs": 6,
          "publishToPickupMs": 55,
          "pickupToWriteMs": 0
        },
        {
          "m": 0,
          "concurrency": 5,
          "sseConnectMs": 197,
          "movePostAckMs": 235,
          "playerEventMs": 691,
          "botMoveTotalMs": 692,
          "lookupMs": 3,
          "applyMs": 7,
          "publishToPickupMs": 434,
          "pickupToWriteMs": 0
        },
        {
          "m": 1,
          "concurrency": 5,
          "sseConnectMs": null,
          "movePostAckMs": 177,
          "playerEventMs": 237,
          "botMoveTotalMs": 237,
          "lookupMs": 2,
          "applyMs": 7,
          "publishToPickupMs": 46,
          "pickupToWriteMs": 0
        },
        {
          "m": 2,
          "concurrency": 5,
          "sseConnectMs": null,
          "movePostAckMs": 260,
          "playerEventMs": 341,
          "botMoveTotalMs": 341,
          "lookupMs": 3,
          "applyMs": 7,
          "publishToPickupMs": 69,
          "pickupToWriteMs": 0
        },
        {
          "m": 0,
          "concurrency": 5,
          "sseConnectMs": 224,
          "movePostAckMs": 183,
          "playerEventMs": 590,
          "botMoveTotalMs": 590,
          "lookupMs": 3,
          "applyMs": 7,
          "publishToPickupMs": 382,
          "pickupToWriteMs": 0
        },
        {
          "m": 1,
          "concurrency": 5,
          "sseConnectMs": null,
          "movePostAckMs": 189,
          "playerEventMs": 247,
          "botMoveTotalMs": 247,
          "lookupMs": 4,
          "applyMs": 5,
          "publishToPickupMs": 49,
          "pickupToWriteMs": 0
        },
        {
          "m": 2,
          "concurrency": 5,
          "sseConnectMs": null,
          "movePostAckMs": 251,
          "playerEventMs": 324,
          "botMoveTotalMs": 324,
          "lookupMs": 3,
          "applyMs": 6,
          "publishToPickupMs": 59,
          "pickupToWriteMs": 0
        },
        {
          "m": 0,
          "concurrency": 5,
          "sseConnectMs": 186,
          "movePostAckMs": 179,
          "playerEventMs": 529,
          "botMoveTotalMs": 529,
          "lookupMs": 3,
          "applyMs": 6,
          "publishToPickupMs": 289,
          "pickupToWriteMs": 0
        },
        {
          "m": 1,
          "concurrency": 5,
          "sseConnectMs": null,
          "movePostAckMs": 201,
          "playerEventMs": 320,
          "botMoveTotalMs": 320,
          "lookupMs": 3,
          "applyMs": 6,
          "publishToPickupMs": 35,
          "pickupToWriteMs": 0
        },
        {
          "m": 2,
          "concurrency": 5,
          "sseConnectMs": null,
          "movePostAckMs": 219,
          "playerEventMs": 191,
          "botMoveTotalMs": 191,
          "lookupMs": 3,
          "applyMs": 7,
          "publishToPickupMs": 9,
          "pickupToWriteMs": 0
        },
        {
          "m": 0,
          "concurrency": 5,
          "sseConnectMs": 162,
          "movePostAckMs": 179,
          "playerEventMs": 512,
          "botMoveTotalMs": 513,
          "lookupMs": 7,
          "applyMs": 8,
          "publishToPickupMs": 254,
          "pickupToWriteMs": 0
        },
        {
          "m": 1,
          "concurrency": 5,
          "sseConnectMs": null,
          "movePostAckMs": 208,
          "playerEventMs": 324,
          "botMoveTotalMs": 324,
          "lookupMs": 2,
          "applyMs": 8,
          "publishToPickupMs": 31,
          "pickupToWriteMs": 0
        },
        {
          "m": 2,
          "concurrency": 5,
          "sseConnectMs": null,
          "movePostAckMs": 167,
          "playerEventMs": 177,
          "botMoveTotalMs": 181,
          "lookupMs": 3,
          "applyMs": 6,
          "publishToPickupMs": 8,
          "pickupToWriteMs": 0
        }
      ]
    },
    {
      "concurrency": 10,
      "movesObserved": 30,
      "usersStarted": 10,
      "fatalUsers": 0,
      "partialUsers": 0,
      "summary": {
        "movePostAck": {
          "p50": 195,
          "p95": 304,
          "p99": 312,
          "n": 30
        },
        "playerEvent": {
          "p50": 276,
          "p95": 612,
          "p99": 923,
          "n": 30
        },
        "botMoveTotal": {
          "p50": 278,
          "p95": 612,
          "p99": 923,
          "n": 30
        },
        "lookup": {
          "p50": 3,
          "p95": 11,
          "p99": 15,
          "n": 30
        },
        "apply": {
          "p50": 7,
          "p95": 18,
          "p99": 23,
          "n": 30
        },
        "publishToPickup": {
          "p50": 32,
          "p95": 406,
          "p99": 732,
          "n": 30
        },
        "pickupToWrite": {
          "p50": 0,
          "p95": 0,
          "p99": 0,
          "n": 30
        }
      },
      "moves": [
        {
          "m": 0,
          "concurrency": 6,
          "sseConnectMs": 83,
          "movePostAckMs": 168,
          "playerEventMs": 923,
          "botMoveTotalMs": 923,
          "lookupMs": 3,
          "applyMs": 8,
          "publishToPickupMs": 732,
          "pickupToWriteMs": 0
        },
        {
          "m": 1,
          "concurrency": 10,
          "sseConnectMs": null,
          "movePostAckMs": 304,
          "playerEventMs": 305,
          "botMoveTotalMs": 305,
          "lookupMs": 2,
          "applyMs": 13,
          "publishToPickupMs": 38,
          "pickupToWriteMs": 0
        },
        {
          "m": 2,
          "concurrency": 10,
          "sseConnectMs": null,
          "movePostAckMs": 192,
          "playerEventMs": 224,
          "botMoveTotalMs": 259,
          "lookupMs": 8,
          "applyMs": 11,
          "publishToPickupMs": 24,
          "pickupToWriteMs": 0
        },
        {
          "m": 0,
          "concurrency": 10,
          "sseConnectMs": 245,
          "movePostAckMs": 195,
          "playerEventMs": 605,
          "botMoveTotalMs": 611,
          "lookupMs": 4,
          "applyMs": 14,
          "publishToPickupMs": 385,
          "pickupToWriteMs": 0
        },
        {
          "m": 1,
          "concurrency": 10,
          "sseConnectMs": null,
          "movePostAckMs": 312,
          "playerEventMs": 315,
          "botMoveTotalMs": 316,
          "lookupMs": 3,
          "applyMs": 6,
          "publishToPickupMs": 45,
          "pickupToWriteMs": 0
        },
        {
          "m": 2,
          "concurrency": 10,
          "sseConnectMs": null,
          "movePostAckMs": 176,
          "playerEventMs": 194,
          "botMoveTotalMs": 196,
          "lookupMs": 3,
          "applyMs": 8,
          "publishToPickupMs": 12,
          "pickupToWriteMs": 0
        },
        {
          "m": 0,
          "concurrency": 10,
          "sseConnectMs": 153,
          "movePostAckMs": 167,
          "playerEventMs": 600,
          "botMoveTotalMs": 600,
          "lookupMs": 3,
          "applyMs": 6,
          "publishToPickupMs": 406,
          "pickupToWriteMs": 0
        },
        {
          "m": 1,
          "concurrency": 10,
          "sseConnectMs": null,
          "movePostAckMs": 166,
          "playerEventMs": 248,
          "botMoveTotalMs": 248,
          "lookupMs": 3,
          "applyMs": 6,
          "publishToPickupMs": 64,
          "pickupToWriteMs": 0
        },
        {
          "m": 2,
          "concurrency": 10,
          "sseConnectMs": null,
          "movePostAckMs": 186,
          "playerEventMs": 247,
          "botMoveTotalMs": 248,
          "lookupMs": 3,
          "applyMs": 6,
          "publishToPickupMs": 50,
          "pickupToWriteMs": 0
        },
        {
          "m": 0,
          "concurrency": 10,
          "sseConnectMs": 91,
          "movePostAckMs": 206,
          "playerEventMs": 612,
          "botMoveTotalMs": 612,
          "lookupMs": 15,
          "applyMs": 7,
          "publishToPickupMs": 365,
          "pickupToWriteMs": 0
        },
        {
          "m": 1,
          "concurrency": 10,
          "sseConnectMs": null,
          "movePostAckMs": 224,
          "playerEventMs": 229,
          "botMoveTotalMs": 229,
          "lookupMs": 2,
          "applyMs": 6,
          "publishToPickupMs": 7,
          "pickupToWriteMs": 0
        },
        {
          "m": 2,
          "concurrency": 10,
          "sseConnectMs": null,
          "movePostAckMs": 192,
          "playerEventMs": 253,
          "botMoveTotalMs": 253,
          "lookupMs": 2,
          "applyMs": 7,
          "publishToPickupMs": 47,
          "pickupToWriteMs": 0
        },
        {
          "m": 0,
          "concurrency": 10,
          "sseConnectMs": 98,
          "movePostAckMs": 167,
          "playerEventMs": 567,
          "botMoveTotalMs": 567,
          "lookupMs": 4,
          "applyMs": 7,
          "publishToPickupMs": 328,
          "pickupToWriteMs": 0
        },
        {
          "m": 1,
          "concurrency": 10,
          "sseConnectMs": null,
          "movePostAckMs": 275,
          "playerEventMs": 279,
          "botMoveTotalMs": 279,
          "lookupMs": 5,
          "applyMs": 16,
          "publishToPickupMs": 11,
          "pickupToWriteMs": 0
        },
        {
          "m": 2,
          "concurrency": 10,
          "sseConnectMs": null,
          "movePostAckMs": 181,
          "playerEventMs": 185,
          "botMoveTotalMs": 215,
          "lookupMs": 3,
          "applyMs": 6,
          "publishToPickupMs": 7,
          "pickupToWriteMs": 0
        },
        {
          "m": 0,
          "concurrency": 10,
          "sseConnectMs": 173,
          "movePostAckMs": 166,
          "playerEventMs": 431,
          "botMoveTotalMs": 431,
          "lookupMs": 2,
          "applyMs": 7,
          "publishToPickupMs": 195,
          "pickupToWriteMs": 0
        },
        {
          "m": 1,
          "concurrency": 10,
          "sseConnectMs": null,
          "movePostAckMs": 297,
          "playerEventMs": 303,
          "botMoveTotalMs": 303,
          "lookupMs": 6,
          "applyMs": 9,
          "publishToPickupMs": 21,
          "pickupToWriteMs": 0
        },
        {
          "m": 2,
          "concurrency": 10,
          "sseConnectMs": null,
          "movePostAckMs": 242,
          "playerEventMs": 274,
          "botMoveTotalMs": 274,
          "lookupMs": 9,
          "applyMs": 23,
          "publishToPickupMs": 19,
          "pickupToWriteMs": 0
        },
        {
          "m": 0,
          "concurrency": 10,
          "sseConnectMs": 168,
          "movePostAckMs": 195,
          "playerEventMs": 330,
          "botMoveTotalMs": 330,
          "lookupMs": 3,
          "applyMs": 9,
          "publishToPickupMs": 70,
          "pickupToWriteMs": 0
        },
        {
          "m": 1,
          "concurrency": 10,
          "sseConnectMs": null,
          "movePostAckMs": 301,
          "playerEventMs": 299,
          "botMoveTotalMs": 302,
          "lookupMs": 10,
          "applyMs": 10,
          "publishToPickupMs": 5,
          "pickupToWriteMs": 0
        },
        {
          "m": 2,
          "concurrency": 10,
          "sseConnectMs": null,
          "movePostAckMs": 176,
          "playerEventMs": 201,
          "botMoveTotalMs": 202,
          "lookupMs": 2,
          "applyMs": 6,
          "publishToPickupMs": 16,
          "pickupToWriteMs": 0
        },
        {
          "m": 0,
          "concurrency": 10,
          "sseConnectMs": 189,
          "movePostAckMs": 250,
          "playerEventMs": 326,
          "botMoveTotalMs": 326,
          "lookupMs": 2,
          "applyMs": 6,
          "publishToPickupMs": 50,
          "pickupToWriteMs": 0
        },
        {
          "m": 1,
          "concurrency": 10,
          "sseConnectMs": null,
          "movePostAckMs": 225,
          "playerEventMs": 222,
          "botMoveTotalMs": 222,
          "lookupMs": 8,
          "applyMs": 18,
          "publishToPickupMs": 12,
          "pickupToWriteMs": 0
        },
        {
          "m": 2,
          "concurrency": 10,
          "sseConnectMs": null,
          "movePostAckMs": 187,
          "playerEventMs": 218,
          "botMoveTotalMs": 268,
          "lookupMs": 5,
          "applyMs": 9,
          "publishToPickupMs": 6,
          "pickupToWriteMs": 0
        },
        {
          "m": 0,
          "concurrency": 10,
          "sseConnectMs": 235,
          "movePostAckMs": 195,
          "playerEventMs": 234,
          "botMoveTotalMs": 234,
          "lookupMs": 2,
          "applyMs": 6,
          "publishToPickupMs": 11,
          "pickupToWriteMs": 0
        },
        {
          "m": 1,
          "concurrency": 10,
          "sseConnectMs": null,
          "movePostAckMs": 218,
          "playerEventMs": 257,
          "botMoveTotalMs": 257,
          "lookupMs": 3,
          "applyMs": 6,
          "publishToPickupMs": 28,
          "pickupToWriteMs": 0
        },
        {
          "m": 2,
          "concurrency": 10,
          "sseConnectMs": null,
          "movePostAckMs": 225,
          "playerEventMs": 259,
          "botMoveTotalMs": 350,
          "lookupMs": 11,
          "applyMs": 15,
          "publishToPickupMs": 14,
          "pickupToWriteMs": 0
        },
        {
          "m": 0,
          "concurrency": 10,
          "sseConnectMs": 177,
          "movePostAckMs": 172,
          "playerEventMs": 236,
          "botMoveTotalMs": 236,
          "lookupMs": 4,
          "applyMs": 6,
          "publishToPickupMs": 35,
          "pickupToWriteMs": 0
        },
        {
          "m": 1,
          "concurrency": 10,
          "sseConnectMs": null,
          "movePostAckMs": 226,
          "playerEventMs": 277,
          "botMoveTotalMs": 277,
          "lookupMs": 5,
          "applyMs": 9,
          "publishToPickupMs": 35,
          "pickupToWriteMs": 0
        },
        {
          "m": 2,
          "concurrency": 9,
          "sseConnectMs": null,
          "movePostAckMs": 251,
          "playerEventMs": 280,
          "botMoveTotalMs": 281,
          "lookupMs": 2,
          "applyMs": 6,
          "publishToPickupMs": 24,
          "pickupToWriteMs": 0
        }
      ]
    },
    {
      "concurrency": 25,
      "movesObserved": 75,
      "usersStarted": 25,
      "fatalUsers": 0,
      "partialUsers": 0,
      "summary": {
        "movePostAck": {
          "p50": 291,
          "p95": 556,
          "p99": 656,
          "n": 75
        },
        "playerEvent": {
          "p50": 376,
          "p95": 721,
          "p99": 1041,
          "n": 75
        },
        "botMoveTotal": {
          "p50": 391,
          "p95": 721,
          "p99": 1041,
          "n": 75
        },
        "lookup": {
          "p50": 9,
          "p95": 121,
          "p99": 199,
          "n": 75
        },
        "apply": {
          "p50": 15,
          "p95": 45,
          "p99": 98,
          "n": 75
        },
        "publishToPickup": {
          "p50": 25,
          "p95": 406,
          "p99": 757,
          "n": 75
        },
        "pickupToWrite": {
          "p50": 0,
          "p95": 0,
          "p99": 0,
          "n": 75
        }
      },
      "moves": [
        {
          "m": 0,
          "concurrency": 6,
          "sseConnectMs": 85,
          "movePostAckMs": 180,
          "playerEventMs": 1041,
          "botMoveTotalMs": 1041,
          "lookupMs": 2,
          "applyMs": 8,
          "publishToPickupMs": 757,
          "pickupToWriteMs": 0
        },
        {
          "m": 1,
          "concurrency": 19,
          "sseConnectMs": null,
          "movePostAckMs": 253,
          "playerEventMs": 251,
          "botMoveTotalMs": 330,
          "lookupMs": 9,
          "applyMs": 15,
          "publishToPickupMs": 10,
          "pickupToWriteMs": 0
        },
        {
          "m": 2,
          "concurrency": 25,
          "sseConnectMs": null,
          "movePostAckMs": 258,
          "playerEventMs": 318,
          "botMoveTotalMs": 319,
          "lookupMs": 14,
          "applyMs": 12,
          "publishToPickupMs": 57,
          "pickupToWriteMs": 0
        },
        {
          "m": 0,
          "concurrency": 7,
          "sseConnectMs": 85,
          "movePostAckMs": 170,
          "playerEventMs": 953,
          "botMoveTotalMs": 953,
          "lookupMs": 4,
          "applyMs": 6,
          "publishToPickupMs": 676,
          "pickupToWriteMs": 0
        },
        {
          "m": 1,
          "concurrency": 20,
          "sseConnectMs": null,
          "movePostAckMs": 417,
          "playerEventMs": 411,
          "botMoveTotalMs": 412,
          "lookupMs": 15,
          "applyMs": 36,
          "publishToPickupMs": 24,
          "pickupToWriteMs": 0
        },
        {
          "m": 2,
          "concurrency": 25,
          "sseConnectMs": null,
          "movePostAckMs": 355,
          "playerEventMs": 465,
          "botMoveTotalMs": 476,
          "lookupMs": 25,
          "applyMs": 33,
          "publishToPickupMs": 21,
          "pickupToWriteMs": 0
        },
        {
          "m": 0,
          "concurrency": 9,
          "sseConnectMs": 80,
          "movePostAckMs": 244,
          "playerEventMs": 770,
          "botMoveTotalMs": 786,
          "lookupMs": 5,
          "applyMs": 23,
          "publishToPickupMs": 416,
          "pickupToWriteMs": 0
        },
        {
          "m": 1,
          "concurrency": 19,
          "sseConnectMs": null,
          "movePostAckMs": 246,
          "playerEventMs": 331,
          "botMoveTotalMs": 332,
          "lookupMs": 16,
          "applyMs": 13,
          "publishToPickupMs": 47,
          "pickupToWriteMs": 0
        },
        {
          "m": 2,
          "concurrency": 24,
          "sseConnectMs": null,
          "movePostAckMs": 293,
          "playerEventMs": 345,
          "botMoveTotalMs": 439,
          "lookupMs": 8,
          "applyMs": 17,
          "publishToPickupMs": 36,
          "pickupToWriteMs": 0
        },
        {
          "m": 0,
          "concurrency": 10,
          "sseConnectMs": 69,
          "movePostAckMs": 202,
          "playerEventMs": 721,
          "botMoveTotalMs": 721,
          "lookupMs": 15,
          "applyMs": 11,
          "publishToPickupMs": 406,
          "pickupToWriteMs": 0
        },
        {
          "m": 1,
          "concurrency": 19,
          "sseConnectMs": null,
          "movePostAckMs": 247,
          "playerEventMs": 335,
          "botMoveTotalMs": 335,
          "lookupMs": 14,
          "applyMs": 14,
          "publishToPickupMs": 47,
          "pickupToWriteMs": 0
        },
        {
          "m": 2,
          "concurrency": 25,
          "sseConnectMs": null,
          "movePostAckMs": 359,
          "playerEventMs": 391,
          "botMoveTotalMs": 392,
          "lookupMs": 17,
          "applyMs": 54,
          "publishToPickupMs": 37,
          "pickupToWriteMs": 0
        },
        {
          "m": 0,
          "concurrency": 14,
          "sseConnectMs": 262,
          "movePostAckMs": 181,
          "playerEventMs": 410,
          "botMoveTotalMs": 410,
          "lookupMs": 3,
          "applyMs": 8,
          "publishToPickupMs": 86,
          "pickupToWriteMs": 0
        },
        {
          "m": 1,
          "concurrency": 20,
          "sseConnectMs": null,
          "movePostAckMs": 404,
          "playerEventMs": 451,
          "botMoveTotalMs": 451,
          "lookupMs": 122,
          "applyMs": 9,
          "publishToPickupMs": 30,
          "pickupToWriteMs": 0
        },
        {
          "m": 2,
          "concurrency": 25,
          "sseConnectMs": null,
          "movePostAckMs": 539,
          "playerEventMs": 420,
          "botMoveTotalMs": 422,
          "lookupMs": 28,
          "applyMs": 20,
          "publishToPickupMs": 42,
          "pickupToWriteMs": 0
        },
        {
          "m": 0,
          "concurrency": 11,
          "sseConnectMs": 154,
          "movePostAckMs": 264,
          "playerEventMs": 678,
          "botMoveTotalMs": 678,
          "lookupMs": 4,
          "applyMs": 7,
          "publishToPickupMs": 277,
          "pickupToWriteMs": 0
        },
        {
          "m": 1,
          "concurrency": 20,
          "sseConnectMs": null,
          "movePostAckMs": 397,
          "playerEventMs": 393,
          "botMoveTotalMs": 393,
          "lookupMs": 20,
          "applyMs": 31,
          "publishToPickupMs": 19,
          "pickupToWriteMs": 0
        },
        {
          "m": 2,
          "concurrency": 25,
          "sseConnectMs": null,
          "movePostAckMs": 341,
          "playerEventMs": 461,
          "botMoveTotalMs": 461,
          "lookupMs": 19,
          "applyMs": 35,
          "publishToPickupMs": 28,
          "pickupToWriteMs": 0
        },
        {
          "m": 0,
          "concurrency": 15,
          "sseConnectMs": 178,
          "movePostAckMs": 185,
          "playerEventMs": 362,
          "botMoveTotalMs": 362,
          "lookupMs": 5,
          "applyMs": 21,
          "publishToPickupMs": 39,
          "pickupToWriteMs": 0
        },
        {
          "m": 1,
          "concurrency": 20,
          "sseConnectMs": null,
          "movePostAckMs": 275,
          "playerEventMs": 314,
          "botMoveTotalMs": 425,
          "lookupMs": 3,
          "applyMs": 14,
          "publishToPickupMs": 7,
          "pickupToWriteMs": 0
        },
        {
          "m": 2,
          "concurrency": 25,
          "sseConnectMs": null,
          "movePostAckMs": 645,
          "playerEventMs": 603,
          "botMoveTotalMs": 603,
          "lookupMs": 185,
          "applyMs": 9,
          "publishToPickupMs": 8,
          "pickupToWriteMs": 0
        },
        {
          "m": 0,
          "concurrency": 14,
          "sseConnectMs": 89,
          "movePostAckMs": 179,
          "playerEventMs": 378,
          "botMoveTotalMs": 378,
          "lookupMs": 3,
          "applyMs": 8,
          "publishToPickupMs": 54,
          "pickupToWriteMs": 0
        },
        {
          "m": 1,
          "concurrency": 20,
          "sseConnectMs": null,
          "movePostAckMs": 409,
          "playerEventMs": 406,
          "botMoveTotalMs": 406,
          "lookupMs": 30,
          "applyMs": 26,
          "publishToPickupMs": 20,
          "pickupToWriteMs": 0
        },
        {
          "m": 2,
          "concurrency": 25,
          "sseConnectMs": null,
          "movePostAckMs": 353,
          "playerEventMs": 450,
          "botMoveTotalMs": 484,
          "lookupMs": 36,
          "applyMs": 22,
          "publishToPickupMs": 15,
          "pickupToWriteMs": 0
        },
        {
          "m": 0,
          "concurrency": 16,
          "sseConnectMs": 196,
          "movePostAckMs": 274,
          "playerEventMs": 459,
          "botMoveTotalMs": 459,
          "lookupMs": 3,
          "applyMs": 10,
          "publishToPickupMs": 166,
          "pickupToWriteMs": 0
        },
        {
          "m": 1,
          "concurrency": 23,
          "sseConnectMs": null,
          "movePostAckMs": 329,
          "playerEventMs": 471,
          "botMoveTotalMs": 471,
          "lookupMs": 2,
          "applyMs": 10,
          "publishToPickupMs": 100,
          "pickupToWriteMs": 0
        },
        {
          "m": 2,
          "concurrency": 24,
          "sseConnectMs": null,
          "movePostAckMs": 434,
          "playerEventMs": 468,
          "botMoveTotalMs": 486,
          "lookupMs": 11,
          "applyMs": 21,
          "publishToPickupMs": 60,
          "pickupToWriteMs": 0
        },
        {
          "m": 0,
          "concurrency": 19,
          "sseConnectMs": 210,
          "movePostAckMs": 193,
          "playerEventMs": 234,
          "botMoveTotalMs": 234,
          "lookupMs": 4,
          "applyMs": 23,
          "publishToPickupMs": 25,
          "pickupToWriteMs": 0
        },
        {
          "m": 1,
          "concurrency": 23,
          "sseConnectMs": null,
          "movePostAckMs": 312,
          "playerEventMs": 441,
          "botMoveTotalMs": 441,
          "lookupMs": 3,
          "applyMs": 8,
          "publishToPickupMs": 60,
          "pickupToWriteMs": 0
        },
        {
          "m": 2,
          "concurrency": 24,
          "sseConnectMs": null,
          "movePostAckMs": 477,
          "playerEventMs": 483,
          "botMoveTotalMs": 544,
          "lookupMs": 21,
          "applyMs": 54,
          "publishToPickupMs": 21,
          "pickupToWriteMs": 0
        },
        {
          "m": 0,
          "concurrency": 20,
          "sseConnectMs": 255,
          "movePostAckMs": 247,
          "playerEventMs": 414,
          "botMoveTotalMs": 414,
          "lookupMs": 4,
          "applyMs": 8,
          "publishToPickupMs": 25,
          "pickupToWriteMs": 0
        },
        {
          "m": 1,
          "concurrency": 25,
          "sseConnectMs": null,
          "movePostAckMs": 556,
          "playerEventMs": 545,
          "botMoveTotalMs": 548,
          "lookupMs": 25,
          "applyMs": 20,
          "publishToPickupMs": 29,
          "pickupToWriteMs": 0
        },
        {
          "m": 2,
          "concurrency": 19,
          "sseConnectMs": null,
          "movePostAckMs": 276,
          "playerEventMs": 261,
          "botMoveTotalMs": 272,
          "lookupMs": 17,
          "applyMs": 10,
          "publishToPickupMs": 7,
          "pickupToWriteMs": 0
        },
        {
          "m": 0,
          "concurrency": 22,
          "sseConnectMs": 243,
          "movePostAckMs": 307,
          "playerEventMs": 325,
          "botMoveTotalMs": 325,
          "lookupMs": 7,
          "applyMs": 21,
          "publishToPickupMs": 21,
          "pickupToWriteMs": 0
        },
        {
          "m": 1,
          "concurrency": 25,
          "sseConnectMs": null,
          "movePostAckMs": 490,
          "playerEventMs": 450,
          "botMoveTotalMs": 450,
          "lookupMs": 99,
          "applyMs": 9,
          "publishToPickupMs": 13,
          "pickupToWriteMs": 0
        },
        {
          "m": 2,
          "concurrency": 18,
          "sseConnectMs": null,
          "movePostAckMs": 300,
          "playerEventMs": 411,
          "botMoveTotalMs": 411,
          "lookupMs": 13,
          "applyMs": 19,
          "publishToPickupMs": 63,
          "pickupToWriteMs": 0
        },
        {
          "m": 0,
          "concurrency": 22,
          "sseConnectMs": 185,
          "movePostAckMs": 234,
          "playerEventMs": 290,
          "botMoveTotalMs": 290,
          "lookupMs": 6,
          "applyMs": 15,
          "publishToPickupMs": 28,
          "pickupToWriteMs": 0
        },
        {
          "m": 1,
          "concurrency": 25,
          "sseConnectMs": null,
          "movePostAckMs": 499,
          "playerEventMs": 421,
          "botMoveTotalMs": 520,
          "lookupMs": 25,
          "applyMs": 25,
          "publishToPickupMs": 14,
          "pickupToWriteMs": 0
        },
        {
          "m": 2,
          "concurrency": 19,
          "sseConnectMs": null,
          "movePostAckMs": 312,
          "playerEventMs": 339,
          "botMoveTotalMs": 411,
          "lookupMs": 3,
          "applyMs": 20,
          "publishToPickupMs": 25,
          "pickupToWriteMs": 0
        },
        {
          "m": 0,
          "concurrency": 25,
          "sseConnectMs": 160,
          "movePostAckMs": 656,
          "playerEventMs": 600,
          "botMoveTotalMs": 602,
          "lookupMs": 199,
          "applyMs": 23,
          "publishToPickupMs": 27,
          "pickupToWriteMs": 0
        },
        {
          "m": 1,
          "concurrency": 19,
          "sseConnectMs": null,
          "movePostAckMs": 291,
          "playerEventMs": 323,
          "botMoveTotalMs": 323,
          "lookupMs": 3,
          "applyMs": 7,
          "publishToPickupMs": 28,
          "pickupToWriteMs": 0
        },
        {
          "m": 2,
          "concurrency": 14,
          "sseConnectMs": null,
          "movePostAckMs": 392,
          "playerEventMs": 383,
          "botMoveTotalMs": 383,
          "lookupMs": 4,
          "applyMs": 12,
          "publishToPickupMs": 19,
          "pickupToWriteMs": 0
        },
        {
          "m": 0,
          "concurrency": 25,
          "sseConnectMs": 348,
          "movePostAckMs": 365,
          "playerEventMs": 495,
          "botMoveTotalMs": 496,
          "lookupMs": 22,
          "applyMs": 18,
          "publishToPickupMs": 57,
          "pickupToWriteMs": 0
        },
        {
          "m": 1,
          "concurrency": 20,
          "sseConnectMs": null,
          "movePostAckMs": 231,
          "playerEventMs": 239,
          "botMoveTotalMs": 391,
          "lookupMs": 24,
          "applyMs": 45,
          "publishToPickupMs": 17,
          "pickupToWriteMs": 0
        },
        {
          "m": 2,
          "concurrency": 15,
          "sseConnectMs": null,
          "movePostAckMs": 235,
          "playerEventMs": 273,
          "botMoveTotalMs": 274,
          "lookupMs": 5,
          "applyMs": 6,
          "publishToPickupMs": 27,
          "pickupToWriteMs": 0
        },
        {
          "m": 0,
          "concurrency": 25,
          "sseConnectMs": 318,
          "movePostAckMs": 555,
          "playerEventMs": 426,
          "botMoveTotalMs": 517,
          "lookupMs": 20,
          "applyMs": 23,
          "publishToPickupMs": 12,
          "pickupToWriteMs": 0
        },
        {
          "m": 1,
          "concurrency": 19,
          "sseConnectMs": null,
          "movePostAckMs": 290,
          "playerEventMs": 280,
          "botMoveTotalMs": 280,
          "lookupMs": 3,
          "applyMs": 9,
          "publishToPickupMs": 5,
          "pickupToWriteMs": 0
        },
        {
          "m": 2,
          "concurrency": 15,
          "sseConnectMs": null,
          "movePostAckMs": 256,
          "playerEventMs": 317,
          "botMoveTotalMs": 317,
          "lookupMs": 3,
          "applyMs": 6,
          "publishToPickupMs": 26,
          "pickupToWriteMs": 0
        },
        {
          "m": 0,
          "concurrency": 25,
          "sseConnectMs": 257,
          "movePostAckMs": 568,
          "playerEventMs": 542,
          "botMoveTotalMs": 543,
          "lookupMs": 121,
          "applyMs": 7,
          "publishToPickupMs": 16,
          "pickupToWriteMs": 0
        },
        {
          "m": 1,
          "concurrency": 19,
          "sseConnectMs": null,
          "movePostAckMs": 308,
          "playerEventMs": 334,
          "botMoveTotalMs": 364,
          "lookupMs": 6,
          "applyMs": 13,
          "publishToPickupMs": 21,
          "pickupToWriteMs": 0
        },
        {
          "m": 2,
          "concurrency": 14,
          "sseConnectMs": null,
          "movePostAckMs": 178,
          "playerEventMs": 285,
          "botMoveTotalMs": 285,
          "lookupMs": 4,
          "applyMs": 6,
          "publishToPickupMs": 19,
          "pickupToWriteMs": 0
        },
        {
          "m": 0,
          "concurrency": 24,
          "sseConnectMs": 244,
          "movePostAckMs": 435,
          "playerEventMs": 477,
          "botMoveTotalMs": 519,
          "lookupMs": 7,
          "applyMs": 16,
          "publishToPickupMs": 61,
          "pickupToWriteMs": 0
        },
        {
          "m": 1,
          "concurrency": 16,
          "sseConnectMs": null,
          "movePostAckMs": 208,
          "playerEventMs": 238,
          "botMoveTotalMs": 256,
          "lookupMs": 23,
          "applyMs": 18,
          "publishToPickupMs": 15,
          "pickupToWriteMs": 0
        },
        {
          "m": 2,
          "concurrency": 13,
          "sseConnectMs": null,
          "movePostAckMs": 350,
          "playerEventMs": 376,
          "botMoveTotalMs": 391,
          "lookupMs": 15,
          "applyMs": 15,
          "publishToPickupMs": 14,
          "pickupToWriteMs": 0
        },
        {
          "m": 0,
          "concurrency": 24,
          "sseConnectMs": 168,
          "movePostAckMs": 443,
          "playerEventMs": 517,
          "botMoveTotalMs": 517,
          "lookupMs": 18,
          "applyMs": 44,
          "publishToPickupMs": 37,
          "pickupToWriteMs": 0
        },
        {
          "m": 1,
          "concurrency": 16,
          "sseConnectMs": null,
          "movePostAckMs": 244,
          "playerEventMs": 254,
          "botMoveTotalMs": 279,
          "lookupMs": 5,
          "applyMs": 18,
          "publishToPickupMs": 17,
          "pickupToWriteMs": 0
        },
        {
          "m": 2,
          "concurrency": 12,
          "sseConnectMs": null,
          "movePostAckMs": 334,
          "playerEventMs": 362,
          "botMoveTotalMs": 362,
          "lookupMs": 12,
          "applyMs": 19,
          "publishToPickupMs": 14,
          "pickupToWriteMs": 0
        },
        {
          "m": 0,
          "concurrency": 19,
          "sseConnectMs": 258,
          "movePostAckMs": 390,
          "playerEventMs": 387,
          "botMoveTotalMs": 387,
          "lookupMs": 58,
          "applyMs": 25,
          "publishToPickupMs": 16,
          "pickupToWriteMs": 0
        },
        {
          "m": 1,
          "concurrency": 15,
          "sseConnectMs": null,
          "movePostAckMs": 152,
          "playerEventMs": 173,
          "botMoveTotalMs": 173,
          "lookupMs": 3,
          "applyMs": 6,
          "publishToPickupMs": 20,
          "pickupToWriteMs": 0
        },
        {
          "m": 2,
          "concurrency": 12,
          "sseConnectMs": null,
          "movePostAckMs": 155,
          "playerEventMs": 205,
          "botMoveTotalMs": 205,
          "lookupMs": 3,
          "applyMs": 14,
          "publishToPickupMs": 32,
          "pickupToWriteMs": 0
        },
        {
          "m": 0,
          "concurrency": 18,
          "sseConnectMs": 370,
          "movePostAckMs": 406,
          "playerEventMs": 428,
          "botMoveTotalMs": 445,
          "lookupMs": 21,
          "applyMs": 98,
          "publishToPickupMs": 25,
          "pickupToWriteMs": 0
        },
        {
          "m": 1,
          "concurrency": 14,
          "sseConnectMs": null,
          "movePostAckMs": 262,
          "playerEventMs": 261,
          "botMoveTotalMs": 261,
          "lookupMs": 5,
          "applyMs": 8,
          "publishToPickupMs": 8,
          "pickupToWriteMs": 0
        },
        {
          "m": 2,
          "concurrency": 10,
          "sseConnectMs": null,
          "movePostAckMs": 174,
          "playerEventMs": 189,
          "botMoveTotalMs": 201,
          "lookupMs": 3,
          "applyMs": 7,
          "publishToPickupMs": 6,
          "pickupToWriteMs": 0
        },
        {
          "m": 0,
          "concurrency": 17,
          "sseConnectMs": 297,
          "movePostAckMs": 383,
          "playerEventMs": 403,
          "botMoveTotalMs": 432,
          "lookupMs": 11,
          "applyMs": 23,
          "publishToPickupMs": 15,
          "pickupToWriteMs": 0
        },
        {
          "m": 1,
          "concurrency": 12,
          "sseConnectMs": null,
          "movePostAckMs": 308,
          "playerEventMs": 331,
          "botMoveTotalMs": 350,
          "lookupMs": 6,
          "applyMs": 28,
          "publishToPickupMs": 13,
          "pickupToWriteMs": 0
        },
        {
          "m": 2,
          "concurrency": 5,
          "sseConnectMs": null,
          "movePostAckMs": 236,
          "playerEventMs": 236,
          "botMoveTotalMs": 236,
          "lookupMs": 3,
          "applyMs": 7,
          "publishToPickupMs": 38,
          "pickupToWriteMs": 0
        },
        {
          "m": 0,
          "concurrency": 16,
          "sseConnectMs": 228,
          "movePostAckMs": 263,
          "playerEventMs": 255,
          "botMoveTotalMs": 296,
          "lookupMs": 15,
          "applyMs": 18,
          "publishToPickupMs": 10,
          "pickupToWriteMs": 0
        },
        {
          "m": 1,
          "concurrency": 12,
          "sseConnectMs": null,
          "movePostAckMs": 333,
          "playerEventMs": 330,
          "botMoveTotalMs": 330,
          "lookupMs": 11,
          "applyMs": 16,
          "publishToPickupMs": 6,
          "pickupToWriteMs": 0
        },
        {
          "m": 2,
          "concurrency": 6,
          "sseConnectMs": null,
          "movePostAckMs": 249,
          "playerEventMs": 254,
          "botMoveTotalMs": 254,
          "lookupMs": 4,
          "applyMs": 7,
          "publishToPickupMs": 71,
          "pickupToWriteMs": 0
        },
        {
          "m": 0,
          "concurrency": 16,
          "sseConnectMs": 294,
          "movePostAckMs": 266,
          "playerEventMs": 258,
          "botMoveTotalMs": 298,
          "lookupMs": 7,
          "applyMs": 16,
          "publishToPickupMs": 8,
          "pickupToWriteMs": 0
        },
        {
          "m": 1,
          "concurrency": 12,
          "sseConnectMs": null,
          "movePostAckMs": 324,
          "playerEventMs": 331,
          "botMoveTotalMs": 355,
          "lookupMs": 18,
          "applyMs": 27,
          "publishToPickupMs": 11,
          "pickupToWriteMs": 0
        },
        {
          "m": 2,
          "concurrency": 6,
          "sseConnectMs": null,
          "movePostAckMs": 249,
          "playerEventMs": 254,
          "botMoveTotalMs": 254,
          "lookupMs": 4,
          "applyMs": 6,
          "publishToPickupMs": 63,
          "pickupToWriteMs": 0
        },
        {
          "m": 0,
          "concurrency": 16,
          "sseConnectMs": 254,
          "movePostAckMs": 231,
          "playerEventMs": 261,
          "botMoveTotalMs": 264,
          "lookupMs": 24,
          "applyMs": 17,
          "publishToPickupMs": 8,
          "pickupToWriteMs": 0
        },
        {
          "m": 1,
          "concurrency": 12,
          "sseConnectMs": null,
          "movePostAckMs": 90,
          "playerEventMs": 203,
          "botMoveTotalMs": 203,
          "lookupMs": 3,
          "applyMs": 8,
          "publishToPickupMs": 17,
          "pickupToWriteMs": 0
        },
        {
          "m": 2,
          "concurrency": 9,
          "sseConnectMs": null,
          "movePostAckMs": 173,
          "playerEventMs": 191,
          "botMoveTotalMs": 191,
          "lookupMs": 2,
          "applyMs": 11,
          "publishToPickupMs": 10,
          "pickupToWriteMs": 0
        }
      ]
    }
  ]
}